{"status": "OK", "error": null, "response": {"header": {"incrementality": 0, "timestamp": 1463595476.921, "gtfs_realtime_version": "1.0"}, "entity": [{"is_deleted": false, "trip_update": {"stop_time_update": {"departure": {"time": 1463595413.983, "delay": 52}, "stop_id": "7642", "stop_sequence": 2, "schedule_relationship": 0}, "timestamp": 1463595413.983, "trip": {"trip_id": "15487002853-20160512154122_v40.34", "schedule_relationship": 0, "route_id": "48704-20160512154122_v40.34"}, "vehicle": {"id": "2929"}}, "id": "3c231946-1477-a571-b039-48e85a49ddee"}, {"is_deleted": false, "trip_update": {"stop_time_update": {"departure": {"time": 1463595437, "delay": 59}, "stop_id": "4615", "stop_sequence": 10, "schedule_relationship": 0}, "timestamp": 1463595437, "trip": {"trip_id": "1982016623-20160512154122_v40.34", "schedule_relationship": 0, "route_id": "98202-20160512154122_v40.34"}, "vehicle": {"id": "3071"}}, "id": "b21430df-7d4f-b4a8-ea4d-70dd39ee02d0"}, {"is_deleted": false, "trip_update": {"stop_time_update": {"departure": {"time": 1463595434.578, "delay": 315}, "stop_id": "4724", "stop_sequence": 16, "schedule_relationship": 0}, "timestamp": 1463595434.578, "trip": {"trip_id": "1983016726-20160512154122_v40.34", "schedule_relationship": 0, "route_id": "98301-20160512154122_v40.34"}, "vehicle": {"id": "3073"}}, "id": "4e40c419-6e9d-3bd0-c635-c48c94f4682f"}, {"is_deleted": false, "trip_update": {"stop_time_update": {"stop_id": "4740", "stop_sequence": 31, "arrival": {"time": 1463595472.91, "delay": 246}, "schedule_relationship": 0}, "timestamp": 1463595472.91, "trip": {"trip_id": "1992033077-20160512154122_v40.34", "schedule_relationship": 0, "route_id": "99201-20160512154122_v40.34"}, "vehicle": {"id": "3081"}}, "id": "8adaf5ab-48e9-7f7e-cdb1-3517be40a0c5"}, {"is_deleted": false, "trip_update": {"stop_time_update": {"departure": {"time": 1463595460.585, "delay": -338}, "stop_id": "4700", "stop_sequence": 58, "schedule_relationship": 0}, "timestamp": 1463595460.585, "trip": {"trip_id": "1982016673-20160512154122_v40.34", "schedule_relationship": 0, "route_id": "98201-20160512154122_v40.34"}, "vehicle": {"id": "3082"}}, "id": "9f5b631d-c121-56ea-8325-a44605b766b5"}, {"is_deleted": false, "trip_update": {"stop_time_update": {"departure": {"time": 1463595446, "delay": 65}, "stop_id": "7419", "stop_sequence": 20, "schedule_relationship": 0}, "timestamp": 1463595446, "trip": {"trip_id": "14625004149-20160512154122_v40.34", "schedule_relationship": 0, "route_id": "62501-20160512154122_v40.34"}, "vehicle": {"id": "3091"}}, "id": "8f74eba1-3351-9ba5-62d9-3564244cc002"}, {"is_deleted": false, "trip_update": {"stop_time_update": {"departure": {"time": 1463595473, "delay": 128}, "stop_id": "3137", "stop_sequence": 35, "schedule_relationship": 0}, "timestamp": 1463595473, "trip": {"trip_id": "12839025249-20160512154122_v40.34", "schedule_relationship": 0, "route_id": "83901-20160512154122_v40.34"}, "vehicle": {"id": "3093"}}, "id": "564941ed-5853-2b26-5b6d-63f71d915149"}, {"is_deleted": false, "trip_update": {"stop_time_update": {"stop_id": "4569", "stop_sequence": 54, "arrival": {"time": 1463595275, "delay": -505}, "schedule_relationship": 0}, "timestamp": 1463595275, "trip": {"trip_id": "1983016724-20160512154122_v40.34", "schedule_relationship": 0, "route_id": "98301-20160512154122_v40.34"}, "vehicle": {"id": "3715"}}, "id": "a18a347c-5683-8034-2cc5-8e0a5ffb65ce"}, {"is_deleted": false, "trip_update": {"stop_time_update": {"departure": {"time": 1463595441.584, "delay": 369}, "stop_id": "7091", "stop_sequence": 69, "schedule_relationship": 0}, "timestamp": 1463595441.584, "trip": {"trip_id": "12837025242-20160512154122_v40.34", "schedule_relationship": 0, "route_id": "83701-20160512154122_v40.34"}, "vehicle": {"id": "3719"}}, "id": "2e4777c3-e991-067d-1a1f-98960a235d97"}, {"is_deleted": false, "trip_update": {"stop_time_update": {"departure": {"time": 1463595433.596, "delay": 25}, "stop_id": "3081", "stop_sequence": 13, "schedule_relationship": 0}, "timestamp": 1463595433.596, "trip": {"trip_id": "12879024961-20160512154122_v40.34", "schedule_relationship": 0, "route_id": "87901-20160512154122_v40.34"}, "vehicle": {"id": "3741"}}, "id": "ef6ed8c8-fada-8224-3b74-36a3c3cf6cc1"}, {"is_deleted": false, "trip_update": {"stop_time_update": {"departure": {"time": 1463595460.274, "delay": 146}, "stop_id": "5837", "stop_sequence": 21, "schedule_relationship": 0}, "timestamp": 1463595460.274, "trip": {"trip_id": "13079019660-20160512154122_v40.34", "schedule_relationship": 0, "route_id": "07901-20160512154122_v40.34"}, "vehicle": {"id": "3749"}}, "id": "268f9e65-df94-7cce-4ce0-11d75b65a4f3"}, {"is_deleted": false, "trip_update": {"stop_time_update": {"departure": {"time": 1463595427.557, "delay": -16}, "stop_id": "8225", "stop_sequence": 17, "schedule_relationship": 0}, "timestamp": 1463595427.557, "trip": {"trip_id": "13223010581-20160512154122_v40.34", "schedule_relationship": 0, "route_id": "22301-20160512154122_v40.34"}, "vehicle": {"id": "3754"}}, "id": "2d62d165-a6ec-2670-e703-9c2f7a4e9db9"}, {"is_deleted": false, "trip_update": {"stop_time_update": {"stop_id": "5112", "stop_sequence": 34, "arrival": {"time": 1463595468.877, "delay": 208}, "schedule_relationship": 0}, "timestamp": 1463595468.877, "trip": {"trip_id": "13087023554-20160512154122_v40.34", "schedule_relationship": 0, "route_id": "08701-20160512154122_v40.34"}, "vehicle": {"id": "3759"}}, "id": "5e506fc2-00d1-59b2-20da-4f2a14da1974"}, {"is_deleted": false, "trip_update": {"stop_time_update": {"departure": {"time": 1463595449.406, "delay": 70}, "stop_id": "7619", "stop_sequence": 67, "schedule_relationship": 0}, "timestamp": 1463595449.406, "trip": {"trip_id": "15471002635-20160512154122_v40.34", "schedule_relationship": 0, "route_id": "47101-20160512154122_v40.34"}, "vehicle": {"id": "3780"}}, "id": "830b065c-4d1d-6428-ced0-215d2c00df2d"}, {"is_deleted": false, "trip_update": {"stop_time_update": {"stop_id": "2024", "stop_sequence": 24, "arrival": {"time": 1463595460.212, "delay": 104}, "schedule_relationship": 0}, "timestamp": 1463595460.212, "trip": {"trip_id": "15375001976-20160512154122_v40.34", "schedule_relationship": 0, "route_id": "37504-20160512154122_v40.34"}, "vehicle": {"id": "3781"}}, "id": "2d6a2c85-9887-4ba8-b045-7065430ce873"}, {"is_deleted": false, "trip_update": {"stop_time_update": {"departure": {"time": 1463595330.841, "delay": 30}, "stop_id": "5914", "stop_sequence": 44, "schedule_relationship": 0}, "timestamp": 1463595330.841, "trip": {"trip_id": "13135025963-20160512154122_v40.34", "schedule_relationship": 0, "route_id": "13501-20160512154122_v40.34"}, "vehicle": {"id": "3786"}}, "id": "68adc2f5-7c94-4e77-a500-c1a8d7eb31d5"}, {"is_deleted": false, "trip_update": {"stop_time_update": {"departure": {"time": 1463595429.421, "delay": 7}, "stop_id": "6704", "stop_sequence": 23, "schedule_relationship": 0}, "timestamp": 1463595429.421, "trip": {"trip_id": "14305013141-20160512154122_v40.34", "schedule_relationship": 0, "route_id": "30501-20160512154122_v40.34"}, "vehicle": {"id": "3789"}}, "id": "b2297315-53f7-d873-3ffe-295013045c09"}, {"is_deleted": false, "trip_update": {"stop_time_update": {"departure": {"time": 1463595457.53, "delay": 93}, "stop_id": "6725", "stop_sequence": 7, "schedule_relationship": 0}, "timestamp": 1463595457.53, "trip": {"trip_id": "15348001789-20160512154122_v40.34", "schedule_relationship": 0, "route_id": "34804-20160512154122_v40.34"}, "vehicle": {"id": "3803"}}, "id": "c99d58ec-b292-8a95-1c2d-4eb18c3b38fc"}, {"is_deleted": false, "trip_update": {"stop_time_update": {"departure": {"time": 1463595456.689, "delay": 59}, "stop_id": "8716", "stop_sequence": 14, "schedule_relationship": 0}, "timestamp": 1463595456.689, "trip": {"trip_id": "14304013106-20160512154122_v40.34", "schedule_relationship": 0, "route_id": "30402-20160512154122_v40.34"}, "vehicle": {"id": "3811"}}, "id": "43666f0c-760b-c9d1-be44-1d4aec1c4d3d"}, {"is_deleted": false, "trip_update": {"stop_time_update": {"stop_id": "6819", "stop_sequence": 18, "arrival": {"time": 1463595467.933, "delay": -113}, "schedule_relationship": 0}, "timestamp": 1463595467.933, "trip": {"trip_id": "15456026260-20160512154122_v40.34", "schedule_relationship": 0, "route_id": "45604-20160512154122_v40.34"}, "vehicle": {"id": "3812"}}, "id": "b769415b-e1c6-92b7-ac3b-83f867260749"}, {"is_deleted": false, "trip_update": {"stop_time_update": {"departure": {"time": 1463595441.479, "delay": 35}, "stop_id": "4110", "stop_sequence": 13, "schedule_relationship": 0}, "timestamp": 1463595441.479, "trip": {"trip_id": "4973028577-20160512154122_v40.34", "schedule_relationship": 0, "route_id": "97302-20160512154122_v40.34"}, "vehicle": {"id": "5209"}}, "id": "9062a242-659a-3a9e-5fe7-142e5e7e9d63"}, {"is_deleted": false, "trip_update": {"stop_time_update": {"departure": {"time": 1463595471.921, "delay": 26}, "stop_id": "4035", "stop_sequence": 13, "schedule_relationship": 0}, "timestamp": 1463595471.921, "trip": {"trip_id": "4976007299-20160512154122_v40.34", "schedule_relationship": 0, "route_id": "97603-20160512154122_v40.34"}, "vehicle": {"id": "5214"}}, "id": "a79c4d5b-c8c5-7c74-1669-a1f9bf100552"}, {"is_deleted": false, "trip_update": {"stop_time_update": {"stop_id": "7034", "stop_sequence": 2, "arrival": {"time": 1463595457.324, "delay": 46}, "schedule_relationship": 0}, "timestamp": 1463595457.324, "trip": {"trip_id": "4974028641-20160512154122_v40.34", "schedule_relationship": 0, "route_id": "97402-20160512154122_v40.34"}, "vehicle": {"id": "5231"}}, "id": "1bcef9fd-c08f-e3b0-c717-7a114e5b1d11"}, {"is_deleted": false, "trip_update": {"stop_time_update": {"departure": {"time": 1463595312.684, "delay": 111}, "stop_id": "3961", "stop_sequence": 32, "schedule_relationship": 0}, "timestamp": 1463595312.684, "trip": {"trip_id": "4966023819-20160512154122_v40.34", "schedule_relationship": 0, "route_id": "96601-20160512154122_v40.34"}, "vehicle": {"id": "5233"}}, "id": "793481a6-e3b7-debd-5648-2a79778a5179"}, {"is_deleted": false, "trip_update": {"stop_time_update": {"departure": {"time": 1463595467.658, "delay": 82}, "stop_id": "3673", "stop_sequence": 2, "schedule_relationship": 0}, "timestamp": 1463595467.658, "trip": {"trip_id": "1060025636-20160512154122_v40.34", "schedule_relationship": 0, "route_id": "95801-20160512154122_v40.34"}, "vehicle": {"id": "5251"}}, "id": "a9fddd27-7d6d-c525-94b5-48b991091fb6"}, {"is_deleted": false, "trip_update": {"stop_time_update": {"departure": {"time": 1463595246, "delay": -432}, "stop_id": "3961", "stop_sequence": 34, "schedule_relationship": 0}, "timestamp": 1463595246, "trip": {"trip_id": "4955028319-20160512154122_v40.34", "schedule_relationship": 0, "route_id": "95501-20160512154122_v40.34"}, "vehicle": {"id": "5253"}}, "id": "555ca6bf-5419-a91f-0fab-d9802ddfe862"}, {"is_deleted": false, "trip_update": {"stop_time_update": {"departure": {"time": 1463595448.648, "delay": 7}, "stop_id": "3010", "stop_sequence": 6, "schedule_relationship": 0}, "timestamp": 1463595448.648, "trip": {"trip_id": "3887005799-20160512154122_v40.34", "schedule_relationship": 0, "route_id": "88705-20160512154122_v40.34"}, "vehicle": {"id": "5603"}}, "id": "82c887c1-5438-ec00-c37e-7ae15e006e6c"}, {"is_deleted": false, "trip_update": {"stop_time_update": {"departure": {"time": 1463595445.459, "delay": -275}, "stop_id": "4223", "stop_sequence": 7, "schedule_relationship": 0}, "timestamp": 1463595445.459, "trip": {"trip_id": "3100008265-20160512154122_v40.34", "schedule_relationship": 0, "route_id": "10004-20160512154122_v40.34"}, "vehicle": {"id": "5738"}}, "id": "f9c477cf-fdf0-d01e-6ccd-26bcf5c107f5"}, {"is_deleted": false, "trip_update": {"stop_time_update": {"departure": {"time": 1463595393.197, "delay": -60}, "stop_id": "4862", "stop_sequence": 33, "schedule_relationship": 0}, "timestamp": 1463595393.197, "trip": {"trip_id": "3060024375-20160512154122_v40.34", "schedule_relationship": 0, "route_id": "06001-20160512154122_v40.34"}, "vehicle": {"id": "5769"}}, "id": "f7d40117-5d61-fd64-9c04-4db830b2ff25"}, {"is_deleted": false, "trip_update": {"stop_time_update": {"stop_id": "7034", "stop_sequence": 2, "arrival": {"time": 1463595421.649, "delay": -4}, "schedule_relationship": 0}, "timestamp": 1463595421.649, "trip": {"trip_id": "3100008500-20160512154122_v40.34", "schedule_relationship": 0, "route_id": "10002-20160512154122_v40.34"}, "vehicle": {"id": "5870"}}, "id": "5e4094db-e1f4-125d-3af2-78d24740598f"}, {"is_deleted": false, "trip_update": {"stop_time_update": {"departure": {"time": 1463595457, "delay": 169}, "stop_id": "4927", "stop_sequence": 5, "schedule_relationship": 0}, "timestamp": 1463595457, "trip": {"trip_id": "3060024376-20160512154122_v40.34", "schedule_relationship": 0, "route_id": "06001-20160512154122_v40.34"}, "vehicle": {"id": "5876"}}, "id": "4c82bde8-41a3-c154-02d3-2c42a8bced20"}, {"is_deleted": false, "trip_update": {"stop_time_update": {"departure": {"time": 1463595448.895, "delay": 30}, "stop_id": "5777", "stop_sequence": 3, "schedule_relationship": 0}, "timestamp": 1463595448.895, "trip": {"trip_id": "3130000809-20160512154122_v40.34", "schedule_relationship": 0, "route_id": "13004-20160512154122_v40.34"}, "vehicle": {"id": "5877"}}, "id": "e8fe7099-d290-775c-29cf-4fe1a0c76b4e"}, {"is_deleted": false, "trip_update": {"stop_time_update": {"departure": {"time": 1463595469.233, "delay": 65}, "stop_id": "3915", "stop_sequence": 4, "schedule_relationship": 0}, "timestamp": 1463595469.233, "trip": {"trip_id": "3920025065-20160512154122_v40.34", "schedule_relationship": 0, "route_id": "92003-20160512154122_v40.34"}, "vehicle": {"id": "5913"}}, "id": "697f50a8-e163-9167-d91c-5e4f2492561b"}, {"is_deleted": false, "trip_update": {"stop_time_update": {"stop_id": "5362", "stop_sequence": 39, "arrival": {"time": 1463595459.724, "delay": 36}, "schedule_relationship": 0}, "timestamp": 1463595459.724, "trip": {"trip_id": "3090020606-20160512154122_v40.34", "schedule_relationship": 0, "route_id": "09001-20160512154122_v40.34"}, "vehicle": {"id": "5943"}}, "id": "37ca1332-810e-29f8-67e5-d657262eb0e8"}, {"is_deleted": false, "trip_update": {"stop_time_update": {"stop_id": "5655", "stop_sequence": 9, "arrival": {"time": 1463595474.563, "delay": 109}, "schedule_relationship": 0}, "timestamp": 1463595474.563, "trip": {"trip_id": "3130023671-20160512154122_v40.34", "schedule_relationship": 0, "route_id": "13005-20160512154122_v40.34"}, "vehicle": {"id": "5946"}}, "id": "4fcbc181-98fd-a34a-398f-820636f5cc95"}, {"is_deleted": false, "trip_update": {"stop_time_update": {"stop_id": "5860", "stop_sequence": 47, "arrival": {"time": 1463595305.945, "delay": -205}, "schedule_relationship": 0}, "timestamp": 1463595305.945, "trip": {"trip_id": "3130023670-20160512154122_v40.34", "schedule_relationship": 0, "route_id": "13005-20160512154122_v40.34"}, "vehicle": {"id": "5947"}}, "id": "0be5f882-d9fa-d26a-31e2-c3a314e87a75"}, {"is_deleted": false, "trip_update": {"stop_time_update": {"departure": {"time": 1463595450, "delay": 199}, "stop_id": "3175", "stop_sequence": 16, "schedule_relationship": 0}, "timestamp": 1463595450, "trip": {"trip_id": "3555003467-20160512154122_v40.34", "schedule_relationship": 0, "route_id": "55501-20160512154122_v40.34"}, "vehicle": {"id": "5971"}}, "id": "ef745786-8069-7736-7a84-ef7043a0e4df"}, {"is_deleted": false, "trip_update": {"stop_time_update": {"departure": {"time": 1463595468.531, "delay": 82}, "stop_id": "3407", "stop_sequence": 3, "schedule_relationship": 0}, "timestamp": 1463595468.531, "trip": {"trip_id": "3813014890-20160512154122_v40.34", "schedule_relationship": 0, "route_id": "81311-20160512154122_v40.34"}, "vehicle": {"id": "5974"}}, "id": "49e7f5b8-c4e2-2b8d-d87e-57ba9a51b206"}, {"is_deleted": false, "trip_update": {"stop_time_update": {"departure": {"time": 1463595460, "delay": -104}, "stop_id": "8508", "stop_sequence": 12, "schedule_relationship": 0}, "timestamp": 1463595460, "trip": {"trip_id": "8300032342-20160512154122_v40.34", "schedule_relationship": 0, "route_id": "30002-20160512154122_v40.34"}, "vehicle": {"id": "6213"}}, "id": "aac2d5d2-3546-348a-1976-bbea7d143288"}, {"is_deleted": false, "trip_update": {"stop_time_update": {"departure": {"time": 1463595432, "delay": -501}, "stop_id": "7147", "stop_sequence": 20, "schedule_relationship": 0}, "timestamp": 1463595432, "trip": {"trip_id": "8300027715-20160512154122_v40.34", "schedule_relationship": 0, "route_id": "30003-20160512154122_v40.34"}, "vehicle": {"id": "6215"}}, "id": "0dfd9088-5ed3-4969-05ef-795783665c43"}, {"is_deleted": false, "trip_update": {"stop_time_update": {"departure": {"time": 1463595431, "delay": 59}, "stop_id": "2699", "stop_sequence": 3, "schedule_relationship": 0}, "timestamp": 1463595431, "trip": {"trip_id": "5550011280-20160512154122_v40.34", "schedule_relationship": 0, "route_id": "55001-20160512154122_v40.34"}, "vehicle": {"id": "5ECD"}}, "id": "7f8bc928-5a7f-ec74-c3f9-b4c6f04fb6e6"}, {"is_deleted": false, "trip_update": {"stop_time_update": {"departure": {"time": 1463595466, "delay": -134}, "stop_id": "3478", "stop_sequence": 19, "schedule_relationship": 0}, "timestamp": 1463595466, "trip": {"trip_id": "3813014977-20160512154122_v40.34", "schedule_relationship": 0, "route_id": "81312-20160512154122_v40.34"}, "vehicle": {"id": "58AC"}}, "id": "f086dae8-d327-4427-8124-dd0ba36ceb1e"}, {"is_deleted": false, "trip_update": {"stop_time_update": {"departure": {"time": 1463595405, "delay": 84}, "stop_id": "2503", "stop_sequence": 15, "schedule_relationship": 0}, "timestamp": 1463595405, "trip": {"trip_id": "15475002787-20160512154122_v40.34", "schedule_relationship": 0, "route_id": "47503-20160512154122_v40.34"}, "vehicle": {"id": "37B9"}}, "id": "2a4ae454-b08d-5505-5596-cdb5a65170c1"}, {"is_deleted": false, "trip_update": {"stop_time_update": {"stop_id": "3107", "stop_sequence": 14, "arrival": {"time": 1463595466.34, "delay": -8}, "schedule_relationship": 0}, "timestamp": 1463595466.34, "trip": {"trip_id": "12858025355-20160512154122_v40.34", "schedule_relationship": 0, "route_id": "85801-20160512154122_v40.34"}, "vehicle": {"id": "30B0"}}, "id": "80ca4103-01d5-128d-707d-ebd98087fdf1"}, {"is_deleted": false, "trip_update": {"stop_time_update": {"departure": {"time": 1463595465.736, "delay": 165}, "stop_id": "7204", "stop_sequence": 9, "schedule_relationship": 0}, "timestamp": 1463595465.736, "trip": {"trip_id": "15532003269-20160512154122_v40.34", "schedule_relationship": 0, "route_id": "53204-20160512154122_v40.34"}, "vehicle": {"id": "36BA"}}, "id": "2a91eec5-8b34-8237-c1c0-2616b2b1c7f0"}, {"is_deleted": false, "trip_update": {"stop_time_update": {"stop_id": "8425", "stop_sequence": 23, "arrival": {"time": 1463595456.94, "delay": 213}, "schedule_relationship": 0}, "timestamp": 1463595456.94, "trip": {"trip_id": "14258012311-20160512154122_v40.34", "schedule_relationship": 0, "route_id": "25801-20160512154122_v40.34"}, "vehicle": {"id": "37F6"}}, "id": "aa511fc1-c4cc-df64-9062-4832fd83b7c7"}, {"is_deleted": false, "trip_update": {"stop_time_update": {"stop_id": "8111", "stop_sequence": 28, "arrival": {"time": 1463595448.116, "delay": -152}, "schedule_relationship": 0}, "timestamp": 1463595448.116, "trip": {"trip_id": "13048019591-20160512154122_v40.34", "schedule_relationship": 0, "route_id": "04801-20160512154122_v40.34"}, "vehicle": {"id": "2F5D"}}, "id": "460b26c2-5b82-1a00-8874-c69c032d6985"}, {"is_deleted": false, "trip_update": {"stop_time_update": {"departure": {"time": 1463595357, "delay": 287}, "stop_id": "5801", "stop_sequence": 15, "schedule_relationship": 0}, "timestamp": 1463595357, "trip": {"trip_id": "13224010665-20160512154122_v40.34", "schedule_relationship": 0, "route_id": "22401-20160512154122_v40.34"}, "vehicle": {"id": "2C8D"}}, "id": "a1dd2f10-e370-66e1-67d9-e8009281f8ba"}, {"is_deleted": false, "trip_update": {"stop_time_update": {"departure": {"time": 1463595374.681, "delay": -371}, "stop_id": "2084", "stop_sequence": 28, "schedule_relationship": 0}, "timestamp": 1463595374.681, "trip": {"trip_id": "5575019856-20160512154122_v40.34", "schedule_relationship": 0, "route_id": "57503-20160512154122_v40.34"}, "vehicle": {"id": "5E60"}}, "id": "337cf407-b604-016e-5774-9273ef492ecf"}, {"is_deleted": false, "trip_update": {"stop_time_update": {"stop_id": "4222", "stop_sequence": 20, "arrival": {"time": 1463595462, "delay": -858}, "schedule_relationship": 0}, "timestamp": 1463595462, "trip": {"trip_id": "1991033067-20160512154122_v40.34", "schedule_relationship": 0, "route_id": "99101-20160512154122_v40.34"}, "vehicle": {"id": "307C"}}, "id": "50de61d6-5aa9-3e30-edcc-9490d92ef8f3"}, {"is_deleted": false, "trip_update": {"stop_time_update": {"stop_id": "6573", "stop_sequence": 44, "arrival": {"time": 1463595471, "delay": 503}, "schedule_relationship": 0}, "timestamp": 1463595471, "trip": {"trip_id": "15338001767-20160512154122_v40.34", "schedule_relationship": 0, "route_id": "33802-20160512154122_v40.34"}, "vehicle": {"id": "2A45"}}, "id": "ede9c632-5bc4-bf4e-4d14-15526aa71527"}, {"is_deleted": false, "trip_update": {"stop_time_update": {"departure": {"time": 1463595463.904, "delay": 525}, "stop_id": "6035", "stop_sequence": 44, "schedule_relationship": 0}, "timestamp": 1463595463.904, "trip": {"trip_id": "15473002769-20160512154122_v40.34", "schedule_relationship": 0, "route_id": "47301-20160512154122_v40.34"}, "vehicle": {"id": "377E"}}, "id": "6a1eab75-6753-4521-3b7e-ef6c2661de5e"}, {"is_deleted": false, "trip_update": {"stop_time_update": {"departure": {"time": 1463595442.92, "delay": 590}, "stop_id": "7205", "stop_sequence": 35, "schedule_relationship": 0}, "timestamp": 1463595442.92, "trip": {"trip_id": "14312013271-20160512154122_v40.34", "schedule_relationship": 0, "route_id": "31201-20160512154122_v40.34"}, "vehicle": {"id": "2C4F"}}, "id": "c25ca086-125e-c94e-2daf-3a4d6d12c8db"}, {"is_deleted": false, "trip_update": {"stop_time_update": {"departure": {"time": 1463595457, "delay": 84}, "stop_id": "6250", "stop_sequence": 3, "schedule_relationship": 0}, "timestamp": 1463595457, "trip": {"trip_id": "5501011419-20160512154122_v40.34", "schedule_relationship": 0, "route_id": "50101-20160512154122_v40.34"}, "vehicle": {"id": "5FB7"}}, "id": "bbb3cd19-5585-a2fd-8ae3-a1db3acb67d2"}, {"is_deleted": false, "trip_update": {"stop_time_update": {"departure": {"time": 1463595381.493, "delay": 113}, "stop_id": "4600", "stop_sequence": 23, "schedule_relationship": 0}, "timestamp": 1463595381.493, "trip": {"trip_id": "1988016973-20160512154122_v40.34", "schedule_relationship": 0, "route_id": "98802-20160512154122_v40.34"}, "vehicle": {"id": "307D"}}, "id": "e48a948d-dcc4-59d9-737e-ff094c14fb9f"}, {"is_deleted": false, "trip_update": {"stop_time_update": {"departure": {"time": 1463595445.406, "delay": 62}, "stop_id": "6345", "stop_sequence": 15, "schedule_relationship": 0}, "timestamp": 1463595445.406, "trip": {"trip_id": "15487002953-20160512154122_v40.34", "schedule_relationship": 0, "route_id": "48701-20160512154122_v40.34"}, "vehicle": {"id": "377B"}}, "id": "0088cc57-630d-6974-c709-23220d6943c1"}, {"is_deleted": false, "trip_update": {"stop_time_update": {"departure": {"time": 1463595421.704, "delay": 86}, "stop_id": "7003", "stop_sequence": 26, "schedule_relationship": 0}, "timestamp": 1463595421.704, "trip": {"trip_id": "14713004439-20160512154122_v40.34", "schedule_relationship": 0, "route_id": "71301-20160512154122_v40.34"}, "vehicle": {"id": "36E5"}}, "id": "fb32bc3a-8d69-4496-a824-4af18a9a0af7"}, {"is_deleted": false, "trip_update": {"stop_time_update": {"departure": {"time": 1463595432.575, "delay": 176}, "stop_id": "8713", "stop_sequence": 14, "schedule_relationship": 0}, "timestamp": 1463595432.575, "trip": {"trip_id": "14302013049-20160512154122_v40.34", "schedule_relationship": 0, "route_id": "30201-20160512154122_v40.34"}, "vehicle": {"id": "2F82"}}, "id": "b35bf0d1-e3e9-dcd3-8cd0-041a14fb262d"}, {"is_deleted": false, "trip_update": {"stop_time_update": {"stop_id": "5458", "stop_sequence": 9, "arrival": {"time": 1463595444.607, "delay": 79}, "schedule_relationship": 0}, "timestamp": 1463595444.607, "trip": {"trip_id": "13154019674-20160512154122_v40.34", "schedule_relationship": 0, "route_id": "15404-20160512154122_v40.34"}, "vehicle": {"id": "2F69"}}, "id": "4bee879b-f3e9-abcf-a5d9-bc4d1b0ace3c"}, {"is_deleted": false, "trip_update": {"stop_time_update": {"departure": {"time": 1463595470.408, "delay": 243}, "stop_id": "3277", "stop_sequence": 42, "schedule_relationship": 0}, "timestamp": 1463595470.408, "trip": {"trip_id": "12875024848-20160512154122_v40.34", "schedule_relationship": 0, "route_id": "87501-20160512154122_v40.34"}, "vehicle": {"id": "2CB5"}}, "id": "4fb626ee-d86b-ecbc-8f4a-bcec82069749"}, {"is_deleted": false, "trip_update": {"stop_time_update": {"departure": {"time": 1463595433.291, "delay": 193}, "stop_id": "7525", "stop_sequence": 36, "schedule_relationship": 0}, "timestamp": 1463595433.291, "trip": {"trip_id": "5500026670-20160512154122_v40.34", "schedule_relationship": 0, "route_id": "50001-20160512154122_v40.34"}, "vehicle": {"id": "5FB4"}}, "id": "109f56a0-56a8-33f8-0262-5f543d59fca3"}, {"is_deleted": false, "trip_update": {"stop_time_update": {"stop_id": "4030", "stop_sequence": 25, "arrival": {"time": 1463595462.233, "delay": 56}, "schedule_relationship": 0}, "timestamp": 1463595462.233, "trip": {"trip_id": "4973028482-20160512154122_v40.34", "schedule_relationship": 0, "route_id": "97301-20160512154122_v40.34"}, "vehicle": {"id": "520D"}}, "id": "201bd79f-62c1-832d-dc70-48936c075aac"}, {"is_deleted": false, "trip_update": {"stop_time_update": {"stop_id": "7086", "stop_sequence": 42, "arrival": {"time": 1463595465.823, "delay": -555}, "schedule_relationship": 0}, "timestamp": 1463595465.823, "trip": {"trip_id": "13221010769-20160512154122_v40.34", "schedule_relationship": 0, "route_id": "22101-20160512154122_v40.34"}, "vehicle": {"id": "37C6"}}, "id": "7b5552b6-7dd0-0f2f-db0e-5067bdbcb6ae"}, {"is_deleted": false, "trip_update": {"stop_time_update": {"departure": {"time": 1463595450.176, "delay": 30}, "stop_id": "6233", "stop_sequence": 11, "schedule_relationship": 0}, "timestamp": 1463595450.176, "trip": {"trip_id": "5580003890-20160512154122_v40.34", "schedule_relationship": 0, "route_id": "58002-20160512154122_v40.34"}, "vehicle": {"id": "5E5A"}}, "id": "109e0d8b-5a15-5f82-0589-a3cb1a2dcf6d"}, {"is_deleted": false, "trip_update": {"stop_time_update": {"stop_id": "1504", "stop_sequence": 15, "arrival": {"time": 1463595470.358, "delay": 69}, "schedule_relationship": 0}, "timestamp": 1463595470.358, "trip": {"trip_id": "18032000223-20160512154122_v40.34", "schedule_relationship": 0, "route_id": "00401-20160512154122_v40.34"}, "vehicle": {"id": "7DD6"}}, "id": "df3bac87-b842-75e4-5dda-d4a24acd69ab"}, {"is_deleted": false, "trip_update": {"stop_time_update": {"departure": {"time": 1463595448, "delay": 202}, "stop_id": "7816", "stop_sequence": 22, "schedule_relationship": 0}, "timestamp": 1463595448, "trip": {"trip_id": "15522003263-20160512154122_v40.34", "schedule_relationship": 0, "route_id": "52201-20160512154122_v40.34"}, "vehicle": {"id": "2CC5"}}, "id": "dcda2b3e-8ab1-1e49-3ebb-74c4363945a2"}, {"is_deleted": false, "trip_update": {"stop_time_update": {"stop_id": "6920", "stop_sequence": 28, "arrival": {"time": 1463595363, "delay": -357}, "schedule_relationship": 0}, "timestamp": 1463595363, "trip": {"trip_id": "15455002314-20160512154122_v40.34", "schedule_relationship": 0, "route_id": "45501-20160512154122_v40.34"}, "vehicle": {"id": "29D4"}}, "id": "ad0950f3-0153-30f5-26fb-168a3a918641"}, {"is_deleted": false, "trip_update": {"stop_time_update": {"departure": {"time": 1463595335.871, "delay": 210}, "stop_id": "7099", "stop_sequence": 2, "schedule_relationship": 0}, "timestamp": 1463595335.871, "trip": {"trip_id": "13224024506-20160512154122_v40.34", "schedule_relationship": 0, "route_id": "22402-20160512154122_v40.34"}, "vehicle": {"id": "2C92"}}, "id": "0e775879-6dd2-00cc-5f50-0d88f31defda"}, {"is_deleted": false, "trip_update": {"stop_time_update": {"stop_id": "6594", "stop_sequence": 43, "arrival": {"time": 1463595473.859, "delay": 8}, "schedule_relationship": 0}, "timestamp": 1463595473.859, "trip": {"trip_id": "7380010376-20160512154122_v40.34", "schedule_relationship": 0, "route_id": "38003-20160512154122_v40.34"}, "vehicle": {"id": "79A5"}}, "id": "eeeb01d2-0d81-2118-47b3-aae8e99eccb1"}, {"is_deleted": false, "trip_update": {"stop_time_update": {"stop_id": "7109", "stop_sequence": 20, "arrival": {"time": 1463595468.041, "delay": -72}, "schedule_relationship": 0}, "timestamp": 1463595468.041, "trip": {"trip_id": "14005009026-20160512154122_v40.34", "schedule_relationship": 0, "route_id": "00501-20160512154122_v40.34"}, "vehicle": {"id": "36E9"}}, "id": "9e43ec19-acec-9dbf-869a-2ccea0fd3a71"}, {"is_deleted": false, "trip_update": {"stop_time_update": {"departure": {"time": 1463595446, "delay": 26}, "stop_id": "4228", "stop_sequence": 1, "schedule_relationship": 0}, "timestamp": 1463595446, "trip": {"trip_id": "12881005552-20160512154122_v40.34", "schedule_relationship": 0, "route_id": "88103-20160512154122_v40.34"}, "vehicle": {"id": "30AD"}}, "id": "a0b219cd-d4a7-2b7a-b465-016880dd2238"}, {"is_deleted": false, "trip_update": {"stop_time_update": {"departure": {"time": 1463595446.554, "delay": 96}, "stop_id": "1039", "stop_sequence": 2, "schedule_relationship": 0}, "timestamp": 1463595446.554, "trip": {"trip_id": "15338001770-20160512154122_v40.34", "schedule_relationship": 0, "route_id": "33802-20160512154122_v40.34"}, "vehicle": {"id": "2C44"}}, "id": "4a3762b7-38be-e275-a92b-b39731501162"}, {"is_deleted": false, "trip_update": {"stop_time_update": {"stop_id": "2537", "stop_sequence": 27, "arrival": {"time": 1463595451.769, "delay": 99}, "schedule_relationship": 0}, "timestamp": 1463595451.769, "trip": {"trip_id": "1004015773-20160512154122_v40.34", "schedule_relationship": 0, "route_id": "47203-20160512154122_v40.34"}, "vehicle": {"id": "309C"}}, "id": "bfd4a691-b035-a89e-c665-68c08edb815d"}, {"is_deleted": false, "trip_update": {"stop_time_update": {"stop_id": "6435", "stop_sequence": 29, "arrival": {"time": 1463595457.45, "delay": -17}, "schedule_relationship": 0}, "timestamp": 1463595457.45, "trip": {"trip_id": "15428002061-20160512154122_v40.34", "schedule_relationship": 0, "route_id": "42801-20160512154122_v40.34"}, "vehicle": {"id": "29D9"}}, "id": "d5979bbf-8266-87f0-929b-e8424cd3cb95"}, {"is_deleted": false, "trip_update": {"stop_time_update": {"departure": {"time": 1463595465, "delay": 53}, "stop_id": "7802", "stop_sequence": 3, "schedule_relationship": 0}, "timestamp": 1463595465, "trip": {"trip_id": "15502003172-20160512154122_v40.34", "schedule_relationship": 0, "route_id": "50201-20160512154122_v40.34"}, "vehicle": {"id": "378D"}}, "id": "0621f33e-0f73-2d45-6679-d63eaa3b7b93"}, {"is_deleted": false, "trip_update": {"stop_time_update": {"departure": {"time": 1463595447.123, "delay": 43}, "stop_id": "2019", "stop_sequence": 3, "schedule_relationship": 0}, "timestamp": 1463595447.123, "trip": {"trip_id": "18179019834-20160512154122_v40.34", "schedule_relationship": 0, "route_id": "56602-20160512154122_v40.34"}, "vehicle": {"id": "5E76"}}, "id": "13b5d4ea-6d1a-8e63-18c6-510afa53a64b"}, {"is_deleted": false, "trip_update": {"stop_time_update": {"departure": {"time": 1463595390.913, "delay": 139}, "stop_id": "3388", "stop_sequence": 19, "schedule_relationship": 0}, "timestamp": 1463595390.913, "trip": {"trip_id": "3555003410-20160512154122_v40.34", "schedule_relationship": 0, "route_id": "55502-20160512154122_v40.34"}, "vehicle": {"id": "57E0"}}, "id": "bbd8a8df-d76d-bba3-1000-0ec80466e6ef"}, {"is_deleted": false, "trip_update": {"stop_time_update": {"departure": {"time": 1463595468, "delay": 35}, "stop_id": "8672", "stop_sequence": 33, "schedule_relationship": 0}, "timestamp": 1463595468, "trip": {"trip_id": "14267012788-20160512154122_v40.34", "schedule_relationship": 0, "route_id": "26702-20160512154122_v40.34"}, "vehicle": {"id": "2C52"}}, "id": "0282e497-9b39-3ba6-5243-c68f9b864062"}, {"is_deleted": false, "trip_update": {"stop_time_update": {"departure": {"time": 1463595474.46, "delay": 85}, "stop_id": "6789", "stop_sequence": 3, "schedule_relationship": 0}, "timestamp": 1463595474.46, "trip": {"trip_id": "1008003576-20160512154122_v40.34", "schedule_relationship": 0, "route_id": "56102-20160512154122_v40.34"}, "vehicle": {"id": "5E72"}}, "id": "df6c46da-ac4c-857e-4ed0-665f10fd700a"}, {"is_deleted": false, "trip_update": {"stop_time_update": {"departure": {"time": 1463595348.068, "delay": 22}, "stop_id": "2052", "stop_sequence": 23, "schedule_relationship": 0}, "timestamp": 1463595348.068, "trip": {"trip_id": "7380010485-20160512154122_v40.34", "schedule_relationship": 0, "route_id": "38004-20160512154122_v40.34"}, "vehicle": {"id": "79A4"}}, "id": "7db10f00-ae5b-bfd4-43f5-ba2c69a42fae"}, {"is_deleted": false, "trip_update": {"stop_time_update": {"departure": {"time": 1463595426.752, "delay": 103}, "stop_id": "8607", "stop_sequence": 35, "schedule_relationship": 0}, "timestamp": 1463595426.752, "trip": {"trip_id": "14299012940-20160512154122_v40.34", "schedule_relationship": 0, "route_id": "29901-20160512154122_v40.34"}, "vehicle": {"id": "2CC2"}}, "id": "eafba29f-3163-ffa4-e29e-019dd7ed2ba7"}, {"is_deleted": false, "trip_update": {"stop_time_update": {"departure": {"time": 1463595435, "delay": 103}, "stop_id": "5656", "stop_sequence": 9, "schedule_relationship": 0}, "timestamp": 1463595435, "trip": {"trip_id": "3130000817-20160512154122_v40.34", "schedule_relationship": 0, "route_id": "13008-20160512154122_v40.34"}, "vehicle": {"id": "585A"}}, "id": "ea47c744-96b7-f34e-8a22-f9f744e4506b"}, {"is_deleted": false, "trip_update": {"stop_time_update": {"departure": {"time": 1463595356.456, "delay": 56}, "stop_id": "7081", "stop_sequence": 1, "schedule_relationship": 0}, "timestamp": 1463595356.456, "trip": {"trip_id": "14030020748-20160512154122_v40.34", "schedule_relationship": 0, "route_id": "03002-20160512154122_v40.34"}, "vehicle": {"id": "36E7"}}, "id": "5c835dfb-3cc5-ff90-6410-aee181dec56d"}, {"is_deleted": false, "trip_update": {"stop_time_update": {"departure": {"time": 1463595440, "delay": 15}, "stop_id": "2559", "stop_sequence": 13, "schedule_relationship": 0}, "timestamp": 1463595440, "trip": {"trip_id": "15473002768-20160512154122_v40.34", "schedule_relationship": 0, "route_id": "47301-20160512154122_v40.34"}, "vehicle": {"id": "2CCD"}}, "id": "202d8ad9-77e4-ddaa-f615-593ba238f780"}, {"is_deleted": false, "trip_update": {"stop_time_update": {"departure": {"time": 1463595327, "delay": 27}, "stop_id": "5640", "stop_sequence": 1, "schedule_relationship": 0}, "timestamp": 1463595327, "trip": {"trip_id": "3090020610-20160512154122_v40.34", "schedule_relationship": 0, "route_id": "09001-20160512154122_v40.34"}, "vehicle": {"id": "57BA"}}, "id": "5f2c3358-6820-a587-90a8-636012327396"}, {"is_deleted": false, "trip_update": {"stop_time_update": {"stop_id": "7615", "stop_sequence": 42, "arrival": {"time": 1463595445.517, "delay": 25}, "schedule_relationship": 0}, "timestamp": 1463595445.517, "trip": {"trip_id": "5550011304-20160512154122_v40.34", "schedule_relationship": 0, "route_id": "55001-20160512154122_v40.34"}, "vehicle": {"id": "5EB2"}}, "id": "127dcec4-7c82-ff61-7eb8-4ea15556cffa"}, {"is_deleted": false, "trip_update": {"stop_time_update": {"departure": {"time": 1463595456.07, "delay": 37}, "stop_id": "3299", "stop_sequence": 4, "schedule_relationship": 0}, "timestamp": 1463595456.07, "trip": {"trip_id": "18089032996-20160512154122_v40.34", "schedule_relationship": 0, "route_id": "87303-20160512154122_v40.34"}, "vehicle": {"id": "372B"}}, "id": "be465abf-e55d-3668-3874-c8fc5b391043"}, {"is_deleted": false, "trip_update": {"stop_time_update": {"departure": {"time": 1463595441.769, "delay": 248}, "stop_id": "7149", "stop_sequence": 19, "schedule_relationship": 0}, "timestamp": 1463595441.769, "trip": {"trip_id": "14274012172-20160512154122_v40.34", "schedule_relationship": 0, "route_id": "27401-20160512154122_v40.34"}, "vehicle": {"id": "2C50"}}, "id": "d64d251c-a44d-623c-4da1-da8cf8b39978"}, {"is_deleted": false, "trip_update": {"stop_time_update": {"departure": {"time": 1463595467.358, "delay": 228}, "stop_id": "8058", "stop_sequence": 39, "schedule_relationship": 0}, "timestamp": 1463595467.358, "trip": {"trip_id": "14007000393-20160512154122_v40.34", "schedule_relationship": 0, "route_id": "00706-20160512154122_v40.34"}, "vehicle": {"id": "37F5"}}, "id": "8d7d26f8-5a31-a049-cf86-860456012227"}, {"is_deleted": false, "trip_update": {"stop_time_update": {"departure": {"time": 1463595458, "delay": 243}, "stop_id": "1403", "stop_sequence": 40, "schedule_relationship": 0}, "timestamp": 1463595458, "trip": {"trip_id": "14769004939-20160512154122_v40.34", "schedule_relationship": 0, "route_id": "76901-20160512154122_v40.34"}, "vehicle": {"id": "36E1"}}, "id": "c3fc5dbc-b6e5-8d99-2860-4f93cefabfb2"}, {"is_deleted": false, "trip_update": {"stop_time_update": {"stop_id": "8207", "stop_sequence": 30, "arrival": {"time": 1463595448.06, "delay": -8}, "schedule_relationship": 0}, "timestamp": 1463595448.06, "trip": {"trip_id": "14243013890-20160512154122_v40.34", "schedule_relationship": 0, "route_id": "24301-20160512154122_v40.34"}, "vehicle": {"id": "2A44"}}, "id": "25af3147-0e30-64b6-c652-9e8f56f80794"}, {"is_deleted": false, "trip_update": {"stop_time_update": {"departure": {"time": 1463595170.141, "delay": -130}, "stop_id": "4226", "stop_sequence": 2, "schedule_relationship": 0}, "timestamp": 1463595170.141, "trip": {"trip_id": "3100026511-20160512154122_v40.34", "schedule_relationship": 0, "route_id": "10003-20160512154122_v40.34"}, "vehicle": {"id": "57D7"}}, "id": "52727111-a126-3f1b-ab2f-fa7fce9119cf"}, {"is_deleted": false, "trip_update": {"stop_time_update": {"departure": {"time": 1463595438.841, "delay": 45}, "stop_id": "6280", "stop_sequence": 3, "schedule_relationship": 0}, "timestamp": 1463595438.841, "trip": {"trip_id": "5575003733-20160512154122_v40.34", "schedule_relationship": 0, "route_id": "57503-20160512154122_v40.34"}, "vehicle": {"id": "5E3B"}}, "id": "054e8765-66b0-ebff-f280-2005ab00b352"}, {"is_deleted": false, "trip_update": {"stop_time_update": {"departure": {"time": 1463595452, "delay": 30}, "stop_id": "8118", "stop_sequence": 13, "schedule_relationship": 0}, "timestamp": 1463595452, "trip": {"trip_id": "1033016140-20160512154122_v40.34", "schedule_relationship": 0, "route_id": "15302-20160512154122_v40.34"}, "vehicle": {"id": "2F67"}}, "id": "30bb3c5f-4cc2-90a9-4a9d-5f9a473fe778"}, {"is_deleted": false, "trip_update": {"stop_time_update": {"departure": {"time": 1463595423.293, "delay": 48}, "stop_id": "3360", "stop_sequence": 4, "schedule_relationship": 0}, "timestamp": 1463595423.293, "trip": {"trip_id": "3100020314-20160512154122_v40.34", "schedule_relationship": 0, "route_id": "10001-20160512154122_v40.34"}, "vehicle": {"id": "57E5"}}, "id": "efa7b011-3671-649e-67d3-5ecbf75ad3ff"}, {"is_deleted": false, "trip_update": {"stop_time_update": {"departure": {"time": 1463595275, "delay": 35}, "stop_id": "4226", "stop_sequence": 1, "schedule_relationship": 0}, "timestamp": 1463595275, "trip": {"trip_id": "3100020315-20160512154122_v40.34", "schedule_relationship": 0, "route_id": "10001-20160512154122_v40.34"}, "vehicle": {"id": "562D"}}, "id": "790b553a-5ac2-ebc0-fee5-75d12559f693"}, {"is_deleted": false, "trip_update": {"stop_time_update": {"departure": {"time": 1463595450, "delay": 389}, "stop_id": "6913", "stop_sequence": 27, "schedule_relationship": 0}, "timestamp": 1463595450, "trip": {"trip_id": "15454002213-20160512154122_v40.34", "schedule_relationship": 0, "route_id": "45401-20160512154122_v40.34"}, "vehicle": {"id": "29D2"}}, "id": "892377e2-f533-1585-4ec6-a10b964c9631"}, {"is_deleted": false, "trip_update": {"stop_time_update": {"departure": {"time": 1463595451.308, "delay": -8}, "stop_id": "2144", "stop_sequence": 3, "schedule_relationship": 0}, "timestamp": 1463595451.308, "trip": {"trip_id": "15454002153-20160512154122_v40.34", "schedule_relationship": 0, "route_id": "45402-20160512154122_v40.34"}, "vehicle": {"id": "37FF"}}, "id": "9792227e-1c29-de9e-8593-141db1b77944"}, {"is_deleted": false, "trip_update": {"stop_time_update": {"departure": {"time": 1463595466.659, "delay": 286}, "stop_id": "7630", "stop_sequence": 56, "schedule_relationship": 0}, "timestamp": 1463595466.659, "trip": {"trip_id": "6008011136-20160512154122_v40.34", "schedule_relationship": 0, "route_id": "00802-20160512154122_v40.34"}, "vehicle": {"id": "5B80"}}, "id": "a99234d6-edc4-8c79-7f7b-7ba5863c115c"}, {"is_deleted": false, "trip_update": {"stop_time_update": {"departure": {"time": 1463595409, "delay": 109}, "stop_id": "1053", "stop_sequence": 1, "schedule_relationship": 0}, "timestamp": 1463595409, "trip": {"trip_id": "14243021122-20160512154122_v40.34", "schedule_relationship": 0, "route_id": "24302-20160512154122_v40.34"}, "vehicle": {"id": "2FBD"}}, "id": "8e7070af-7093-4c1f-d339-0922c5915baa"}, {"is_deleted": false, "trip_update": {"stop_time_update": {"departure": {"time": 1463595391, "delay": 67}, "stop_id": "5973", "stop_sequence": 21, "schedule_relationship": 0}, "timestamp": 1463595391, "trip": {"trip_id": "3080026125-20160512154122_v40.34", "schedule_relationship": 0, "route_id": "08001-20160512154122_v40.34"}, "vehicle": {"id": "56D9"}}, "id": "3d6f2ab9-efa0-1e52-95e8-424d6a284d81"}, {"is_deleted": false, "trip_update": {"stop_time_update": {"stop_id": "5914", "stop_sequence": 37, "arrival": {"time": 1463595475, "delay": -125}, "schedule_relationship": 0}, "timestamp": 1463595475, "trip": {"trip_id": "13113000682-20160512154122_v40.34", "schedule_relationship": 0, "route_id": "11303-20160512154122_v40.34"}, "vehicle": {"id": "37C0"}}, "id": "3ba85178-e542-2980-320e-fce691e31a8d"}, {"is_deleted": false, "trip_update": {"stop_time_update": {"stop_id": "7271", "stop_sequence": 26, "arrival": {"time": 1463595469.927, "delay": 326}, "schedule_relationship": 0}, "timestamp": 1463595469.927, "trip": {"trip_id": "14745004640-20160512154122_v40.34", "schedule_relationship": 0, "route_id": "74503-20160512154122_v40.34"}, "vehicle": {"id": "377F"}}, "id": "8f748ccb-4241-20e9-6579-18950d4d5a2f"}, {"is_deleted": false, "trip_update": {"stop_time_update": {"stop_id": "7004", "stop_sequence": 8, "arrival": {"time": 1463595458.368, "delay": -212}, "schedule_relationship": 0}, "timestamp": 1463595458.368, "trip": {"trip_id": "3100020313-20160512154122_v40.34", "schedule_relationship": 0, "route_id": "10001-20160512154122_v40.34"}, "vehicle": {"id": "562E"}}, "id": "62a69fb6-0ab7-3897-6d3a-a827cd026346"}, {"is_deleted": false, "trip_update": {"stop_time_update": {"departure": {"time": 1463595448.048, "delay": -26}, "stop_id": "6059", "stop_sequence": 25, "schedule_relationship": 0}, "timestamp": 1463595448.048, "trip": {"trip_id": "5550011279-20160512154122_v40.34", "schedule_relationship": 0, "route_id": "55001-20160512154122_v40.34"}, "vehicle": {"id": "5E99"}}, "id": "92850b8a-6316-926b-7bcc-a0d64d00d279"}, {"is_deleted": false, "trip_update": {"stop_time_update": {"stop_id": "3885", "stop_sequence": 20, "arrival": {"time": 1463595455.1, "delay": -199}, "schedule_relationship": 0}, "timestamp": 1463595455.1, "trip": {"trip_id": "4955028318-20160512154122_v40.34", "schedule_relationship": 0, "route_id": "95501-20160512154122_v40.34"}, "vehicle": {"id": "524D"}}, "id": "87bf21ad-54a4-33da-3963-59ffbaa37404"}, {"is_deleted": false, "trip_update": {"stop_time_update": {"departure": {"time": 1463595456, "delay": 85}, "stop_id": "8088", "stop_sequence": 19, "schedule_relationship": 0}, "timestamp": 1463595456, "trip": {"trip_id": "14020029287-20160512154122_v40.34", "schedule_relationship": 0, "route_id": "02002-20160512154122_v40.34"}, "vehicle": {"id": "2CBF"}}, "id": "67cccaf6-962e-4483-4c88-0db92c61d39b"}, {"is_deleted": false, "trip_update": {"stop_time_update": {"departure": {"time": 1463595406.213, "delay": 106}, "stop_id": "6525", "stop_sequence": 11, "schedule_relationship": 0}, "timestamp": 1463595406.213, "trip": {"trip_id": "15328001645-20160512154122_v40.34", "schedule_relationship": 0, "route_id": "32801-20160512154122_v40.34"}, "vehicle": {"id": "2A01"}}, "id": "7bcf64ea-e17e-ad09-86e9-ccedd843a650"}, {"is_deleted": false, "trip_update": {"stop_time_update": {"departure": {"time": 1463595461, "delay": 195}, "stop_id": "8314", "stop_sequence": 20, "schedule_relationship": 0}, "timestamp": 1463595461, "trip": {"trip_id": "14249013743-20160512154122_v40.34", "schedule_relationship": 0, "route_id": "24902-20160512154122_v40.34"}, "vehicle": {"id": "37DC"}}, "id": "8a1e05ab-bf7b-e4d0-0214-542ca3b82b46"}, {"is_deleted": false, "trip_update": {"stop_time_update": {"departure": {"time": 1463595432.532, "delay": -69}, "stop_id": "6164", "stop_sequence": 12, "schedule_relationship": 0}, "timestamp": 1463595432.532, "trip": {"trip_id": "5552011880-20160512154122_v40.34", "schedule_relationship": 0, "route_id": "55201-20160512154122_v40.34"}, "vehicle": {"id": "5EC3"}}, "id": "caa9939f-d8c7-0b1e-360e-072f77aa9ed0"}, {"is_deleted": false, "trip_update": {"stop_time_update": {"departure": {"time": 1463595421.873, "delay": 116}, "stop_id": "6569", "stop_sequence": 35, "schedule_relationship": 0}, "timestamp": 1463595421.873, "trip": {"trip_id": "15497003099-20160512154122_v40.34", "schedule_relationship": 0, "route_id": "49701-20160512154122_v40.34"}, "vehicle": {"id": "29FF"}}, "id": "15548b92-c297-094f-176e-536ed35f6e09"}, {"is_deleted": false, "trip_update": {"stop_time_update": {"departure": {"time": 1463595411.519, "delay": 159}, "stop_id": "6048", "stop_sequence": 46, "schedule_relationship": 0}, "timestamp": 1463595411.519, "trip": {"trip_id": "15454002135-20160512154122_v40.34", "schedule_relationship": 0, "route_id": "45402-20160512154122_v40.34"}, "vehicle": {"id": "292A"}}, "id": "73a16557-1fd3-7aab-d45e-f2018c9ce387"}, {"is_deleted": false, "trip_update": {"stop_time_update": {"departure": {"time": 1463595419.655, "delay": 127}, "stop_id": "4789", "stop_sequence": 21, "schedule_relationship": 0}, "timestamp": 1463595419.655, "trip": {"trip_id": "1981016570-20160512154122_v40.34", "schedule_relationship": 0, "route_id": "98101-20160512154122_v40.34"}, "vehicle": {"id": "2CB6"}}, "id": "b828b1d0-c954-0668-127c-a27bfd3af95e"}, {"is_deleted": false, "trip_update": {"stop_time_update": {"departure": {"time": 1463595465.419, "delay": -15}, "stop_id": "8526", "stop_sequence": 20, "schedule_relationship": 0}, "timestamp": 1463595465.419, "trip": {"trip_id": "14274012285-20160512154122_v40.34", "schedule_relationship": 0, "route_id": "27402-20160512154122_v40.34"}, "vehicle": {"id": "2F4F"}}, "id": "2647241f-4195-55ed-0a3d-e412bd863c74"}, {"is_deleted": false, "trip_update": {"stop_time_update": {"stop_id": "5287", "stop_sequence": 35, "arrival": {"time": 1463595471.811, "delay": 64}, "schedule_relationship": 0}, "timestamp": 1463595471.811, "trip": {"trip_id": "13154019682-20160512154122_v40.34", "schedule_relationship": 0, "route_id": "15401-20160512154122_v40.34"}, "vehicle": {"id": "375D"}}, "id": "014901d3-4828-b2c2-a0b8-ed1e086ffbfa"}, {"is_deleted": false, "trip_update": {"stop_time_update": {"departure": {"time": 1463595253, "delay": 562}, "stop_id": "8155", "stop_sequence": 68, "schedule_relationship": 0}, "timestamp": 1463595253, "trip": {"trip_id": "15338001769-20160512154122_v40.34", "schedule_relationship": 0, "route_id": "33802-20160512154122_v40.34"}, "vehicle": {"id": "2C97"}}, "id": "c3b5e695-f27e-c549-9b4b-f05c85415fad"}, {"is_deleted": false, "trip_update": {"stop_time_update": {"departure": {"time": 1463595422.804, "delay": 80}, "stop_id": "6367", "stop_sequence": 7, "schedule_relationship": 0}, "timestamp": 1463595422.804, "trip": {"trip_id": "15375001970-20160512154122_v40.34", "schedule_relationship": 0, "route_id": "37504-20160512154122_v40.34"}, "vehicle": {"id": "2C47"}}, "id": "f60e0c35-6855-738a-c6b1-6712e5b5401a"}, {"is_deleted": false, "trip_update": {"stop_time_update": {"departure": {"time": 1463595472.308, "delay": 78}, "stop_id": "5182", "stop_sequence": 3, "schedule_relationship": 0}, "timestamp": 1463595472.308, "trip": {"trip_id": "1045025571-20160512154122_v40.34", "schedule_relationship": 0, "route_id": "19501-20160512154122_v40.34"}, "vehicle": {"id": "5BBC"}}, "id": "cf9e98e7-3d84-f823-a059-837800e31672"}, {"is_deleted": false, "trip_update": {"stop_time_update": {"departure": {"time": 1463595455.707, "delay": 97}, "stop_id": "6763", "stop_sequence": 3, "schedule_relationship": 0}, "timestamp": 1463595455.707, "trip": {"trip_id": "5568003601-20160512154122_v40.34", "schedule_relationship": 0, "route_id": "56802-20160512154122_v40.34"}, "vehicle": {"id": "5E49"}}, "id": "1e4de3d7-af28-ee50-052b-ef3650275c58"}, {"is_deleted": false, "trip_update": {"stop_time_update": {"stop_id": "4195", "stop_sequence": 10, "arrival": {"time": 1463595449.584, "delay": -49}, "schedule_relationship": 0}, "timestamp": 1463595449.584, "trip": {"trip_id": "12881023748-20160512154122_v40.34", "schedule_relationship": 0, "route_id": "88101-20160512154122_v40.34"}, "vehicle": {"id": "2CBC"}}, "id": "6fbd78e1-2541-db44-2951-73d9bc0e588b"}, {"is_deleted": false, "trip_update": {"stop_time_update": {"departure": {"time": 1463595468.37, "delay": 63}, "stop_id": "3157", "stop_sequence": 12, "schedule_relationship": 0}, "timestamp": 1463595468.37, "trip": {"trip_id": "12875024856-20160512154122_v40.34", "schedule_relationship": 0, "route_id": "87501-20160512154122_v40.34"}, "vehicle": {"id": "30AE"}}, "id": "3a0f4bcc-e6f5-4e0d-0aa4-d59f9ac350c4"}, {"is_deleted": false, "trip_update": {"stop_time_update": {"departure": {"time": 1463595437, "delay": 236}, "stop_id": "2529", "stop_sequence": 17, "schedule_relationship": 0}, "timestamp": 1463595437, "trip": {"trip_id": "15471002645-20160512154122_v40.34", "schedule_relationship": 0, "route_id": "47101-20160512154122_v40.34"}, "vehicle": {"id": "37CC"}}, "id": "1fbb0754-693d-dab6-4b3f-c9807c08d600"}, {"is_deleted": false, "trip_update": {"stop_time_update": {"stop_id": "1213", "stop_sequence": 23, "arrival": {"time": 1463595441.428, "delay": 102}, "schedule_relationship": 0}, "timestamp": 1463595441.428, "trip": {"trip_id": "18025027769-20160512154122_v40.34", "schedule_relationship": 0, "route_id": "00201-20160512154122_v40.34"}, "vehicle": {"id": "7D68"}}, "id": "145c3487-049e-b889-12f9-19948cd808af"}, {"is_deleted": false, "trip_update": {"stop_time_update": {"departure": {"time": 1463595471.69, "delay": 103}, "stop_id": "2161", "stop_sequence": 18, "schedule_relationship": 0}, "timestamp": 1463595471.69, "trip": {"trip_id": "15334001732-20160512154122_v40.34", "schedule_relationship": 0, "route_id": "33403-20160512154122_v40.34"}, "vehicle": {"id": "29D7"}}, "id": "cf9fd5e7-1a83-c624-4530-2538030f9199"}, {"is_deleted": false, "trip_update": {"stop_time_update": {"departure": {"time": 1463595389, "delay": 89}, "stop_id": "4569", "stop_sequence": 1, "schedule_relationship": 0}, "timestamp": 1463595389, "trip": {"trip_id": "3100026512-20160512154122_v40.34", "schedule_relationship": 0, "route_id": "10003-20160512154122_v40.34"}, "vehicle": {"id": "576D"}}, "id": "bfa94f33-b1b2-0128-f569-4a4463964e3c"}, {"is_deleted": false, "trip_update": {"stop_time_update": {"departure": {"time": 1463595355.154, "delay": 369}, "stop_id": "8137", "stop_sequence": 51, "schedule_relationship": 0}, "timestamp": 1463595355.154, "trip": {"trip_id": "1033026182-20160512154122_v40.34", "schedule_relationship": 0, "route_id": "15301-20160512154122_v40.34"}, "vehicle": {"id": "2F62"}}, "id": "34b2a2af-b057-93a7-9b38-cbdb0d0a72b7"}, {"is_deleted": false, "trip_update": {"stop_time_update": {"stop_id": "7201", "stop_sequence": 65, "arrival": {"time": 1463595433.481, "delay": -107}, "schedule_relationship": 0}, "timestamp": 1463595433.481, "trip": {"trip_id": "15497003092-20160512154122_v40.34", "schedule_relationship": 0, "route_id": "49701-20160512154122_v40.34"}, "vehicle": {"id": "378C"}}, "id": "a5c4cc83-0b53-2f42-86b9-7d349e977d9d"}, {"is_deleted": false, "trip_update": {"stop_time_update": {"departure": {"time": 1463595327, "delay": 27}, "stop_id": "7026", "stop_sequence": 1, "schedule_relationship": 0}, "timestamp": 1463595327, "trip": {"trip_id": "14274026817-20160512154122_v40.34", "schedule_relationship": 0, "route_id": "27402-20160512154122_v40.34"}, "vehicle": {"id": "2F70"}}, "id": "673895ca-40a3-fbef-4c4a-09399e9680f5"}, {"is_deleted": false, "trip_update": {"stop_time_update": {"departure": {"time": 1463595457.989, "delay": 17}, "stop_id": "8679", "stop_sequence": 4, "schedule_relationship": 0}, "timestamp": 1463595457.989, "trip": {"trip_id": "14299026043-20160512154122_v40.34", "schedule_relationship": 0, "route_id": "29901-20160512154122_v40.34"}, "vehicle": {"id": "2F81"}}, "id": "5a8e75b9-a5d8-53ff-0fcd-18f67e142a64"}, {"is_deleted": false, "trip_update": {"stop_time_update": {"departure": {"time": 1463595428.582, "delay": 280}, "stop_id": "8661", "stop_sequence": 40, "schedule_relationship": 0}, "timestamp": 1463595428.582, "trip": {"trip_id": "5552011874-20160512154122_v40.34", "schedule_relationship": 0, "route_id": "55201-20160512154122_v40.34"}, "vehicle": {"id": "5ECC"}}, "id": "798a31fe-2be8-c179-9b57-dcc8a31f19a3"}, {"is_deleted": false, "trip_update": {"stop_time_update": {"stop_id": "7988", "stop_sequence": 38, "arrival": {"time": 1463595470.115, "delay": 61}, "schedule_relationship": 0}, "timestamp": 1463595470.115, "trip": {"trip_id": "14756004703-20160512154122_v40.34", "schedule_relationship": 0, "route_id": "75601-20160512154122_v40.34"}, "vehicle": {"id": "36F8"}}, "id": "8cc175a6-083c-8a50-1a9d-384c4c861c2c"}, {"is_deleted": false, "trip_update": {"stop_time_update": {"departure": {"time": 1463595173.198, "delay": 133}, "stop_id": "7036", "stop_sequence": 6, "schedule_relationship": 0}, "timestamp": 1463595173.198, "trip": {"trip_id": "12839025309-20160512154122_v40.34", "schedule_relationship": 0, "route_id": "83902-20160512154122_v40.34"}, "vehicle": {"id": "37EF"}}, "id": "9cc861bd-17f3-6fa4-3698-e4e3281b18e9"}, {"is_deleted": false, "trip_update": {"stop_time_update": {"departure": {"time": 1463595404.515, "delay": 22}, "stop_id": "2159", "stop_sequence": 2, "schedule_relationship": 0}, "timestamp": 1463595404.515, "trip": {"trip_id": "5589004326-20160512154122_v40.34", "schedule_relationship": 0, "route_id": "58903-20160512154122_v40.34"}, "vehicle": {"id": "5E6D"}}, "id": "e90e7b77-82b1-2ca9-d1f8-f0fa6cd4473a"}, {"is_deleted": false, "trip_update": {"stop_time_update": {"departure": {"time": 1463595424, "delay": 300}, "stop_id": "7086", "stop_sequence": 32, "schedule_relationship": 0}, "timestamp": 1463595424, "trip": {"trip_id": "13223010594-20160512154122_v40.34", "schedule_relationship": 0, "route_id": "22301-20160512154122_v40.34"}, "vehicle": {"id": "37BF"}}, "id": "8f6cd292-fcdc-06b2-8d5a-9be85fe0d096"}, {"is_deleted": false, "trip_update": {"stop_time_update": {"stop_id": "7415", "stop_sequence": 3, "arrival": {"time": 1463595465.449, "delay": 20}, "schedule_relationship": 0}, "timestamp": 1463595465.449, "trip": {"trip_id": "14703028139-20160512154122_v40.34", "schedule_relationship": 0, "route_id": "70301-20160512154122_v40.34"}, "vehicle": {"id": "37DB"}}, "id": "55d84f41-fe96-d82c-6e21-07a76e037024"}, {"is_deleted": false, "trip_update": {"stop_time_update": {"departure": {"time": 1463595468.946, "delay": -12}, "stop_id": "6987", "stop_sequence": 19, "schedule_relationship": 0}, "timestamp": 1463595468.946, "trip": {"trip_id": "5500026667-20160512154122_v40.34", "schedule_relationship": 0, "route_id": "50001-20160512154122_v40.34"}, "vehicle": {"id": "5EC9"}}, "id": "5b77b96f-c940-1bbd-616f-7bccc8b86c90"}, {"is_deleted": false, "trip_update": {"stop_time_update": {"departure": {"time": 1463595465.227, "delay": 143}, "stop_id": "5759", "stop_sequence": 10, "schedule_relationship": 0}, "timestamp": 1463595465.227, "trip": {"trip_id": "13097019664-20160512154122_v40.34", "schedule_relationship": 0, "route_id": "09701-20160512154122_v40.34"}, "vehicle": {"id": "37BC"}}, "id": "fd2e381a-4189-14cc-4033-79d8d9127c1a"}, {"is_deleted": false, "trip_update": {"stop_time_update": {"departure": {"time": 1463595472.744, "delay": 225}, "stop_id": "8445", "stop_sequence": 15, "schedule_relationship": 0}, "timestamp": 1463595472.744, "trip": {"trip_id": "14267024615-20160512154122_v40.34", "schedule_relationship": 0, "route_id": "26701-20160512154122_v40.34"}, "vehicle": {"id": "2CA4"}}, "id": "d2cfd7c5-9e39-ba77-0cd6-71436cd3a086"}, {"is_deleted": false, "trip_update": {"stop_time_update": {"departure": {"time": 1463595393.946, "delay": 279}, "stop_id": "6482", "stop_sequence": 34, "schedule_relationship": 0}, "timestamp": 1463595393.946, "trip": {"trip_id": "7380010484-20160512154122_v40.34", "schedule_relationship": 0, "route_id": "38004-20160512154122_v40.34"}, "vehicle": {"id": "79A6"}}, "id": "e26456ce-f982-a916-2c9d-5a42e262e33c"}, {"is_deleted": false, "trip_update": {"stop_time_update": {"departure": {"time": 1463595450, "delay": 130}, "stop_id": "8834", "stop_sequence": 23, "schedule_relationship": 0}, "timestamp": 1463595450, "trip": {"trip_id": "6008011150-20160512154122_v40.34", "schedule_relationship": 0, "route_id": "00802-20160512154122_v40.34"}, "vehicle": {"id": "5BA3"}}, "id": "1b5487ac-38bb-cf3d-798e-dbd76761814a"}, {"is_deleted": false, "trip_update": {"stop_time_update": {"departure": {"time": 1463595454.537, "delay": 334}, "stop_id": "2006", "stop_sequence": 2, "schedule_relationship": 0}, "timestamp": 1463595454.537, "trip": {"trip_id": "8300024119-20160512154122_v40.34", "schedule_relationship": 0, "route_id": "30005-20160512154122_v40.34"}, "vehicle": {"id": "621F"}}, "id": "b716fc02-604d-e49e-4fce-f3ba57958c9a"}, {"is_deleted": false, "trip_update": {"stop_time_update": {"departure": {"time": 1463595443.667, "delay": -6}, "stop_id": "7085", "stop_sequence": 25, "schedule_relationship": 0}, "timestamp": 1463595443.667, "trip": {"trip_id": "14020029196-20160512154122_v40.34", "schedule_relationship": 0, "route_id": "02001-20160512154122_v40.34"}, "vehicle": {"id": "36FB"}}, "id": "c25611a9-5b27-ea2c-cb2e-8d4974a64e27"}, {"is_deleted": false, "trip_update": {"stop_time_update": {"departure": {"time": 1463595469.17, "delay": 95}, "stop_id": "8953", "stop_sequence": 26, "schedule_relationship": 0}, "timestamp": 1463595469.17, "trip": {"trip_id": "6009015140-20160512154122_v40.34", "schedule_relationship": 0, "route_id": "00906-20160512154122_v40.34"}, "vehicle": {"id": "5BBD"}}, "id": "865c2861-8313-9e25-afe3-6ffb025376eb"}, {"is_deleted": false, "trip_update": {"stop_time_update": {"stop_id": "5787", "stop_sequence": 20, "arrival": {"time": 1463595470.615, "delay": 27}, "schedule_relationship": 0}, "timestamp": 1463595470.615, "trip": {"trip_id": "13135000905-20160512154122_v40.34", "schedule_relationship": 0, "route_id": "13503-20160512154122_v40.34"}, "vehicle": {"id": "2F6B"}}, "id": "700707f1-8d7d-705c-5db5-5e6318d21f4b"}, {"is_deleted": false, "trip_update": {"stop_time_update": {"departure": {"time": 1463595397.553, "delay": -215}, "stop_id": "8139", "stop_sequence": 39, "schedule_relationship": 0}, "timestamp": 1463595397.553, "trip": {"trip_id": "1045025567-20160512154122_v40.34", "schedule_relationship": 0, "route_id": "19501-20160512154122_v40.34"}, "vehicle": {"id": "5BB6"}}, "id": "c050c609-b6a7-e446-f065-7b67fcd5d70e"}, {"is_deleted": false, "trip_update": {"stop_time_update": {"departure": {"time": 1463595227.296, "delay": 429}, "stop_id": "2196", "stop_sequence": 17, "schedule_relationship": 0}, "timestamp": 1463595227.296, "trip": {"trip_id": "7380010377-20160512154122_v40.34", "schedule_relationship": 0, "route_id": "38003-20160512154122_v40.34"}, "vehicle": {"id": "79A7"}}, "id": "3b913d5a-b6f6-482f-c711-0d807bcafedb"}, {"is_deleted": false, "trip_update": {"stop_time_update": {"stop_id": "4037", "stop_sequence": 12, "arrival": {"time": 1463595450.598, "delay": -60}, "schedule_relationship": 0}, "timestamp": 1463595450.598, "trip": {"trip_id": "4974028595-20160512154122_v40.34", "schedule_relationship": 0, "route_id": "97401-20160512154122_v40.34"}, "vehicle": {"id": "523D"}}, "id": "281b2460-2c2e-4233-77e2-ed18629d3825"}, {"is_deleted": false, "trip_update": {"stop_time_update": {"departure": {"time": 1463595441.612, "delay": 564}, "stop_id": "1182", "stop_sequence": 24, "schedule_relationship": 0}, "timestamp": 1463595441.612, "trip": {"trip_id": "18023033130-20160512154122_v40.34", "schedule_relationship": 0, "route_id": "00302-20160512154122_v40.34"}, "vehicle": {"id": "7D96"}}, "id": "e439a129-8e90-7dd0-b4cf-2372e56473dd"}, {"is_deleted": false, "trip_update": {"stop_time_update": {"departure": {"time": 1463595420, "delay": 118}, "stop_id": "6571", "stop_sequence": 32, "schedule_relationship": 0}, "timestamp": 1463595420, "trip": {"trip_id": "15359001956-20160512154122_v40.34", "schedule_relationship": 0, "route_id": "35902-20160512154122_v40.34"}, "vehicle": {"id": "2A20"}}, "id": "e3e6c223-58bd-83d6-5812-0c0ca3e4029f"}, {"is_deleted": false, "trip_update": {"stop_time_update": {"departure": {"time": 1463595441, "delay": 32}, "stop_id": "6622", "stop_sequence": 27, "schedule_relationship": 0}, "timestamp": 1463595441, "trip": {"trip_id": "15344001775-20160512154122_v40.34", "schedule_relationship": 0, "route_id": "34403-20160512154122_v40.34"}, "vehicle": {"id": "380D"}}, "id": "f5c6df79-5551-bd55-a09e-e5bf19eedfb5"}, {"is_deleted": false, "trip_update": {"stop_time_update": {"departure": {"time": 1463595469.747, "delay": 199}, "stop_id": "8121", "stop_sequence": 54, "schedule_relationship": 0}, "timestamp": 1463595469.747, "trip": {"trip_id": "13087023550-20160512154122_v40.34", "schedule_relationship": 0, "route_id": "08701-20160512154122_v40.34"}, "vehicle": {"id": "37C3"}}, "id": "4ddc3f4a-aec4-25eb-e5a4-5ea5347ae476"}, {"is_deleted": false, "trip_update": {"stop_time_update": {"departure": {"time": 1463595415.452, "delay": 9}, "stop_id": "6771", "stop_sequence": 2, "schedule_relationship": 0}, "timestamp": 1463595415.452, "trip": {"trip_id": "18021032462-20160512154122_v40.34", "schedule_relationship": 0, "route_id": "48705-20160512154122_v40.34"}, "vehicle": {"id": "37FC"}}, "id": "26b3373b-78d6-cecd-2d4e-659db46f5852"}, {"is_deleted": false, "trip_update": {"stop_time_update": {"departure": {"time": 1463595454, "delay": 80}, "stop_id": "3653", "stop_sequence": 12, "schedule_relationship": 0}, "timestamp": 1463595454, "trip": {"trip_id": "3905005963-20160512154122_v40.34", "schedule_relationship": 0, "route_id": "90503-20160512154122_v40.34"}, "vehicle": {"id": "576A"}}, "id": "929e3852-8b82-eb34-aa3b-a51dcd8c3c1d"}, {"is_deleted": false, "trip_update": {"stop_time_update": {"departure": {"time": 1463595446, "delay": 107}, "stop_id": "8267", "stop_sequence": 28, "schedule_relationship": 0}, "timestamp": 1463595446, "trip": {"trip_id": "14249013687-20160512154122_v40.34", "schedule_relationship": 0, "route_id": "24901-20160512154122_v40.34"}, "vehicle": {"id": "2FB6"}}, "id": "f20a0f95-5a41-c872-6d72-ea65fc41b1ed"}, {"is_deleted": false, "trip_update": {"stop_time_update": {"departure": {"time": 1463595450, "delay": 35}, "stop_id": "6059", "stop_sequence": 23, "schedule_relationship": 0}, "timestamp": 1463595450, "trip": {"trip_id": "5501011413-20160512154122_v40.34", "schedule_relationship": 0, "route_id": "50101-20160512154122_v40.34"}, "vehicle": {"id": "5E97"}}, "id": "dad26f30-0321-3ff9-2989-62ad4dd57267"}, {"is_deleted": false, "trip_update": {"stop_time_update": {"departure": {"time": 1463595421.638, "delay": 121}, "stop_id": "8866", "stop_sequence": 17, "schedule_relationship": 0}, "timestamp": 1463595421.638, "trip": {"trip_id": "13222010908-20160512154122_v40.34", "schedule_relationship": 0, "route_id": "22202-20160512154122_v40.34"}, "vehicle": {"id": "2F6A"}}, "id": "d72797f7-b411-4298-9184-b0fb0d4e2b74"}, {"is_deleted": false, "trip_update": {"stop_time_update": {"stop_id": "7971", "stop_sequence": 29, "arrival": {"time": 1463595468.048, "delay": 36}, "schedule_relationship": 0}, "timestamp": 1463595468.048, "trip": {"trip_id": "14756004663-20160512154122_v40.34", "schedule_relationship": 0, "route_id": "75602-20160512154122_v40.34"}, "vehicle": {"id": "36ED"}}, "id": "c19a681c-6850-75d5-d17f-d74bf2dc8b91"}, {"is_deleted": false, "trip_update": {"stop_time_update": {"departure": {"time": 1463595404.358, "delay": 110}, "stop_id": "4540", "stop_sequence": 16, "schedule_relationship": 0}, "timestamp": 1463595404.358, "trip": {"trip_id": "1985016868-20160512154122_v40.34", "schedule_relationship": 0, "route_id": "98501-20160512154122_v40.34"}, "vehicle": {"id": "2C59"}}, "id": "e9868def-a251-ecd2-d814-f3c81d7e1b58"}, {"is_deleted": false, "trip_update": {"stop_time_update": {"stop_id": "1200", "stop_sequence": 10, "arrival": {"time": 1463595443, "delay": 92}, "schedule_relationship": 0}, "timestamp": 1463595443, "trip": {"trip_id": "17101000253-20160512154122_v40.34", "schedule_relationship": 0, "route_id": "00105-20160512154122_v40.34"}, "vehicle": {"id": "7D98"}}, "id": "e9460806-9c18-2ba5-0cfa-0587b6a3a2ef"}]}}